tagfiles/__init__.py
tagfiles/_common.py
tagfiles/base.py
tagfiles/errors.py
tagfiles/id3.py
tagfiles/mp4.py
tagfiles/vorbis.py
tagfiles-0.3.3.dist-info/LICENSE
tagfiles-0.3.3.dist-info/WHEEL
tagfiles-0.3.3.dist-info/METADATA
tagfiles-0.3.3.dist-info/RECORD
