Metadata-Version: 2.1
Name: tagfiles
Version: 0.3.3
Summary: A tagging interface for multiple audio formats and metadata containers.
Home-page: https://github.com/azuline/tagfiles
License: Apache-2.0
Author: azuline
Author-email: azuline@riseup.net
Requires-Python: >=3.6,<4.0
Classifier: License :: OSI Approved :: Apache Software License
Classifier: Programming Language :: Python :: 3
Classifier: Programming Language :: Python :: 3.6
Classifier: Programming Language :: Python :: 3.7
Classifier: Programming Language :: Python :: 3.8
Classifier: Programming Language :: Python :: 3.9
Requires-Dist: mutagen (>=1.42,<2.0)
Project-URL: Repository, https://github.com/azuline/tagfiles
